LICENSE
MANIFEST.in
README.md
setup.py
config/install_requires.txt
config/project_name.txt
xs_lib/ConstraintDict.py
xs_lib/__init__.py
xs_lib/common.py
xs_lib/ismain.py
xs_lib/template.py
xs_lib/timer.py
xs_lib/version.py
xs_lib.egg-info/PKG-INFO
xs_lib.egg-info/SOURCES.txt
xs_lib.egg-info/dependency_links.txt
xs_lib.egg-info/entry_points.txt
xs_lib.egg-info/requires.txt
xs_lib.egg-info/top_level.txt