Metadata-Version: 2.1
Name: xs-lib
Version: 0.1.0
Summary: personal lib
Home-page: https://github.com/xsthunder/xs_lib
Author: xsthunder
Author-email: xsthunder@outlook.com
License: UNKNOWN
Platform: UNKNOWN
Classifier: Programming Language :: Python :: 3
Classifier: License :: OSI Approved :: MIT License
Classifier: Operating System :: OS Independent
Requires-Python: >=3.4
